tantri/__init__.py
tantri/binning/__init__.py
tantri/binning/binning.py
tantri/cli/__init__.py
tantri/cli/file_importer.py
tantri/cli/input_files/__init__.py
tantri/cli/input_files/read_dipoles.py
tantri/cli/input_files/read_dots.py
tantri/cli/input_files/write_dipoles.py
tantri/dipoles/__init__.py
tantri/dipoles/event_time_series.py
tantri/dipoles/generation/__init__.py
tantri/dipoles/generation/generate_dipole_config.py
tantri/dipoles/supersample.py
tantri/dipoles/time_series.py
tantri/dipoles/types.py
tantri/meta.py
tantri/simple_telegraph/__init__.py
tantri/util.py
tantri-1.3.0.dist-info/METADATA
tantri-1.3.0.dist-info/WHEEL
tantri-1.3.0.dist-info/entry_points.txt
tantri-1.3.0.dist-info/RECORD
